lightmorphic/__init__.py
lightmorphic/main.py
lightmorphic/release.py
lightmorphic/constants/__init__.py
lightmorphic/constants/ct.py
lightmorphic/constants/tests/test_const.py
lightmorphic/database/__init__.py
lightmorphic/database/db_keys.py
lightmorphic/database/atmospheric_domain/__init__.py
lightmorphic/database/atmospheric_domain/adlsa.py
lightmorphic/database/atmospheric_domain/adlsa_RO.py
lightmorphic/database/atmospheric_domain/Romania/__init__.py
lightmorphic/database/atmospheric_domain/Romania/Alba/Abrud/AB_Abrud.py
lightmorphic/database/atmospheric_domain/Romania/Alba/Aiud/AB_Aiud.py
lightmorphic/database/atmospheric_domain/Romania/Alba/Alba_Iulia/AB_Alba_Iulia.py
lightmorphic/database/atmospheric_domain/Romania/Alba/Baia_de_Aries/AB_Baia_de_Aries.py
lightmorphic/database/atmospheric_domain/Romania/Alba/Blaj/AB_Blaj.py
lightmorphic/database/atmospheric_domain/Romania/Alba/Campeni/AB_Campeni.py
lightmorphic/database/atmospheric_domain/Romania/Alba/Cugir/AB_Cugir.py
lightmorphic/database/atmospheric_domain/Romania/Alba/Ocna_Mures/AB_Ocna_Mures.py
lightmorphic/database/atmospheric_domain/Romania/Alba/Sebes/AB_Sebes.py
lightmorphic/database/atmospheric_domain/Romania/Alba/Teius/AB_Teius.py
lightmorphic/database/atmospheric_domain/Romania/Alba/Zlatna/AB_Zlatna.py
lightmorphic/database/atmospheric_domain/Romania/Arad/Arad/AR_Arad.py
lightmorphic/database/atmospheric_domain/Romania/Arad/Chisineu_Cris/AR_Chisineu_Cris.py
lightmorphic/database/atmospheric_domain/Romania/Arad/Curtici/AR_Curtici.py
lightmorphic/database/atmospheric_domain/Romania/Arad/Ineu/AR_Ineu.py
lightmorphic/database/atmospheric_domain/Romania/Arad/Lipova/AR_Lipova.py
lightmorphic/database/atmospheric_domain/Romania/Arad/Nadlac/AR_Nadlac.py
lightmorphic/database/atmospheric_domain/Romania/Arad/Pancota/AR_Pancota.py
lightmorphic/database/atmospheric_domain/Romania/Arad/Pecica/AR_Pecica.py
lightmorphic/database/atmospheric_domain/Romania/Arad/Santana/AR_Santana.py
lightmorphic-0.1.1.dist-info/LICENSE
lightmorphic-0.1.1.dist-info/METADATA
lightmorphic-0.1.1.dist-info/WHEEL
lightmorphic-0.1.1.dist-info/top_level.txt
lightmorphic-0.1.1.dist-info/RECORD
