Metadata-Version: 2.1
Name: lightmorphic
Version: 0.1.1
Summary: Lightmorphic signatures analysis toolkit (LSAT)
Author-email: ARXDE <info@arxde.ro>
Project-URL: Homepage, https://www.arxde.ro/laborator.html
Keywords: lightmorphic,spatiotemporal,spectrogram,,graph chord,neural network
Classifier: Development Status :: 3 - Alpha
Classifier: Intended Audience :: Science/Research
Classifier: Intended Audience :: Education
Classifier: Intended Audience :: End Users/Desktop
Classifier: Intended Audience :: Developers
Classifier: Natural Language :: English
Classifier: Topic :: Scientific/Engineering
Classifier: Topic :: Scientific/Engineering :: Mathematics
Classifier: Topic :: Scientific/Engineering :: Astronomy
Classifier: Topic :: Scientific/Engineering :: Atmospheric Science 
Classifier: License :: OSI Approved :: MIT License
Classifier: Programming Language :: Python :: 3
Classifier: Environment :: Web Environment
Classifier: Operating System :: OS Independent
Requires-Python: >=3.10
License-File: LICENSE
